ancypwn_backend_unix/__init__.py
ancypwn_backend_unix/backend.py
ancypwn_backend_unix-0.0.2.dist-info/METADATA
ancypwn_backend_unix-0.0.2.dist-info/WHEEL
ancypwn_backend_unix-0.0.2.dist-info/top_level.txt
ancypwn_backend_unix-0.0.2.dist-info/RECORD
