Metadata-Version: 2.1
Name: ancypwn-backend-unix
Version: 0.0.2
Summary: ancypwn unix universal backend
Home-page: https://github.com/Escapingbug/ancypwn-backend-unix
Author: Anciety
Author-email: anciety@pku.edu.cn
License: UNKNOWN
Platform: UNKNOWN
Requires-Dist: docker
Requires-Dist: appdirs
Requires-Dist: daemonize
